sfsdk/__init__.py
sfsdk/cli.py
sfsdk/containers.py
sfsdk/imgsettings.py
sfsdk/log.py
sfsdk/sfsdkwatch.py
sfsdk/utils.py
sfsdk/web.py
sfsdk/static/assets/css/lib.css
sfsdk/static/assets/css/style.css
sfsdk/static/assets/fonts/fontawesome-webfont.eot
sfsdk/static/assets/fonts/fontawesome-webfont.svg
sfsdk/static/assets/fonts/fontawesome-webfont.ttf
sfsdk/static/assets/fonts/fontawesome-webfont.woff
sfsdk/static/assets/fonts/fontawesome-webfont.woff2
sfsdk/static/assets/fonts/glyphicons-halflings-regular.eot
sfsdk/static/assets/fonts/glyphicons-halflings-regular.svg
sfsdk/static/assets/fonts/glyphicons-halflings-regular.ttf
sfsdk/static/assets/fonts/glyphicons-halflings-regular.woff
sfsdk/static/assets/img/emptyExercises.png
sfsdk/static/assets/img/favicon-96x96.png
sfsdk/static/assets/img/loader.gif
sfsdk/static/assets/img/sfhn.png
sfsdk/static/assets/img/toastui-editor-2x.png
sfsdk/static/assets/img/toastui-editor.png
sfsdk/static/assets/js/libm.min.js
sfsdk/static/assets/js/management.js
sfsdk/templates/index.html
sfsdk-2.2.1.dist-info/licenses/LICENSE.txt
sfsdk-2.2.1.dist-info/METADATA
sfsdk-2.2.1.dist-info/WHEEL
sfsdk-2.2.1.dist-info/entry_points.txt
sfsdk-2.2.1.dist-info/top_level.txt
sfsdk-2.2.1.dist-info/RECORD
