Metadata-Version: 2.4
Name: sfsdk
Version: 2.2.1
Summary: SDK for the SecureFlag training platform
Author-email: SecureFlag <info@secureflag.com>
License: GPL-3.0-or-later
Project-URL: Homepage, https://gitlab.com/secureflag-community/sdk
Classifier: Programming Language :: Python :: 3
Classifier: Intended Audience :: Developers
Classifier: Natural Language :: English
Classifier: Operating System :: OS Independent
Classifier: License :: OSI Approved :: GNU General Public License v3 or later (GPLv3+)
License-File: LICENSE.txt
Requires-Dist: ruamel.yaml
Requires-Dist: Flask
Requires-Dist: jinja2
Requires-Dist: PyYAML
Requires-Dist: docker
Requires-Dist: prettytable
Requires-Dist: simplejson
Requires-Dist: argcomplete
Dynamic: license-file
